xbimer_cli/__assets__.py
xbimer_cli/__http__.py
xbimer_cli/__init__.py
xbimer_cli/__token__.py
xbimer_cli/__version__.py
xbimer_cli/__vsproj__.py
xbimer_cli/applet.py
xbimer_cli/clis.py
xbimer_cli/module.py
xbimer_cli/set_token.py
xbimer_cli/version.py
xbimer_cli/whoami.py
xbimer_cli/assets/applet/README.md
xbimer_cli/assets/applet/default.png
xbimer_cli/assets/applet/main.py
xbimer_cli/assets/config/mac/.gitkeep
xbimer_cli/assets/config/win/includes_ac22.json
xbimer_cli/assets/config/win/includes_ac23.json
xbimer_cli/assets/config/win/includes_ac24.json
xbimer_cli/assets/config/win/includes_none.json
xbimer_cli/assets/config/win/libraries_ac22.json
xbimer_cli/assets/config/win/libraries_ac23.json
xbimer_cli/assets/config/win/libraries_ac24.json
xbimer_cli/assets/config/win/libraries_none.json
xbimer_cli/assets/module/libs/.gitkeep
xbimer_cli/assets/module/src/__entry__.cpp
xbimer_cli/assets/module/src/dllmain.cpp
xbimer_cli/assets/module/src/stdafx.cpp
xbimer_cli/assets/module/src/stdafx.h
xbimer_cli/assets/module/src/targetver.h
xbimer_cli/assets/ziplibs/Python37.zip
xbimer_cli/assets/ziplibs/ac22.zip
xbimer_cli/assets/ziplibs/ac23.zip
xbimer_cli/assets/ziplibs/ac24.zip
xbimer_cli/assets/ziplibs/cast.zip
xbimer_cli/assets/ziplibs/pybind11.zip
xbimer_cli-2.0.3.dist-info/LICENSE
xbimer_cli-2.0.3.dist-info/METADATA
xbimer_cli-2.0.3.dist-info/WHEEL
xbimer_cli-2.0.3.dist-info/entry_points.txt
xbimer_cli-2.0.3.dist-info/top_level.txt
xbimer_cli-2.0.3.dist-info/RECORD
